LICENSE
MANIFEST.in
README.md
pyproject.toml
setup.cfg
setup.py
polt/__init__.py
polt/__main__.py
polt/config.py
polt/extensions.py
polt/l10n.py
polt/registry.py
polt/streamer.py
polt/utils.py
polt/version.py
polt.egg-info/PKG-INFO
polt.egg-info/SOURCES.txt
polt.egg-info/dependency_links.txt
polt.egg-info/entry_points.txt
polt.egg-info/requires.txt
polt.egg-info/top_level.txt
polt/animator/__init__.py
polt/animator/hist.py
polt/animator/lines.py
polt/animator/spectrum.py
polt/animator/subplots.py
polt/animator/timelines.py
polt/cli/__init__.py
polt/cli/__main__.py
polt/cli/utils.py
polt/cli/commands/__init__.py
polt/cli/commands/add_filter.py
polt/cli/commands/add_source.py
polt/cli/commands/config.py
polt/cli/commands/generate.py
polt/cli/commands/live.py
polt/cli/commands/main.py
polt/filter/__init__.py
polt/filter/calculate.py
polt/filter/metadata.py
polt/filter/select.py
polt/locale/de/LC_MESSAGES/polt.mo
polt/parser/__init__.py
polt/parser/csvparser.py
polt/parser/mosquittoparser.py
polt/parser/numberparser.py
polt/parser/parser.py