Metadata-Version: 2.1
Name: polt
Version: 1.1.0
Summary: Live data visualisation via Matplotlib
Home-page: https://gitlab.com/nobodyinperson/python3-polt
Author: Yann Buechau
Author-email: nobodyinperson@gmx.de
License: GPLv3
Keywords: live,plot,plotting,data,visualisation,matplotlib
Classifier: License :: OSI Approved :: GNU General Public License v3 (GPLv3)
Classifier: Programming Language :: Python :: 3.4
Classifier: Programming Language :: Python :: 3.5
Classifier: Programming Language :: Python :: 3.6
Classifier: Programming Language :: Python :: 3.7
Classifier: Intended Audience :: Science/Research
Classifier: Topic :: Multimedia :: Graphics :: Presentation
Classifier: Topic :: Multimedia :: Graphics :: Viewers
Classifier: Topic :: Scientific/Engineering
Classifier: Development Status :: 4 - Beta
Requires-Python: >=3.4
License-File: LICENSE
